sheetFeeder/__init__.py
sheetFeeder/sheetFeeder.py
sheetFeeder-0.2.3.dist-info/LICENSE.txt
sheetFeeder-0.2.3.dist-info/METADATA
sheetFeeder-0.2.3.dist-info/WHEEL
sheetFeeder-0.2.3.dist-info/top_level.txt
sheetFeeder-0.2.3.dist-info/RECORD
