Metadata-Version: 2.1
Name: sheetFeeder
Version: 0.2.3
Summary: Python tool set for interacting with Google Sheets data.
Home-page: https://github.com/dwhodges2/sheetFeeder
Author: David W Hodges
Author-email: dwhodges@gmail.com
License: MIT
Keywords: googlesheets api tabular data
Platform: UNKNOWN
Classifier: Programming Language :: Python :: 3
Classifier: License :: OSI Approved :: MIT License
Classifier: Operating System :: OS Independent
Requires-Python: >=3.4.0
Requires-Dist: requests
Requires-Dist: google-api-python-client
Requires-Dist: oauth2client
